{"version":2,"kind":"Article","sha256":"7f6d7ef0a4f84c2ea6c4c835ab6721834452c4b6cde42caf3ef2ba05778a353f","slug":"index","location":"/README.md","dependencies":[],"frontmatter":{"title":"MPAS+JEDI Cookbook","content_includes_title":false,"authors":[{"nameParsed":{"literal":"Guoqing Ge","given":"Guoqing","family":"Ge"},"name":"Guoqing Ge","id":"contributors-myst-generated-uid-0"},{"nameParsed":{"literal":"Orhan Eroglu","given":"Orhan","family":"Eroglu"},"name":"Orhan Eroglu","id":"contributors-myst-generated-uid-1"},{"nameParsed":{"literal":"Yan Pan","given":"Yan","family":"Pan"},"name":"Yan Pan","id":"contributors-myst-generated-uid-2"},{"nameParsed":{"literal":"Haidao Lin","given":"Haidao","family":"Lin"},"name":"Haidao Lin","id":"contributors-myst-generated-uid-3"},{"nameParsed":{"literal":"Stephen Asare","given":"Stephen","family":"Asare"},"name":"Stephen Asare","id":"contributors-myst-generated-uid-4"},{"nameParsed":{"literal":"Altug Karakurt","given":"Altug","family":"Karakurt"},"name":"Altug Karakurt","id":"contributors-myst-generated-uid-5"},{"nameParsed":{"literal":"Philip Chmielowiec","given":"Philip","family":"Chmielowiec"},"name":"Philip Chmielowiec","id":"contributors-myst-generated-uid-6"}],"open_access":true,"license":{"content":{"id":"CC-BY-4.0","url":"https://creativecommons.org/licenses/by/4.0/","name":"Creative Commons Attribution 4.0 International","free":true,"CC":true},"code":{"id":"Apache-2.0","url":"https://opensource.org/licenses/Apache-2.0","name":"Apache License 2.0","free":true,"osi":true}},"github":"https://github.com/projectpythia/mpas-jedi-cookbook","copyright":"2025","affiliations":[{"id":"UAlbany","name":"University at Albany (SUNY)","department":"Atmospheric and Environmental Sciences","url":"https://www.albany.edu/daes"},{"id":"CISL","name":"NSF National Center for Atmospheric Research","department":"Computational and Information Systems Lab","url":"https://www.cisl.ucar.edu"},{"id":"Unidata","name":"NSF Unidata","url":"https://www.unidata.ucar.edu"},{"id":"Argonne","name":"Argonne National Laboratory","department":"Environmental Science Division","url":"https://www.anl.gov/evs"},{"id":"CarbonPlan","name":"CarbonPlan","url":"https://carbonplan.org"},{"id":"NVIDIA","name":"NVIDIA Corporation","url":"https://www.nvidia.com/"}],"abbreviations":{"MPAS":"Model for Prediction Across Scales","JEDI":"Joint Effort for Data Assimilation Integration","RRFS":"Rapid Refresh Forecast System","DA":"Data Assimilation","CIRES":"Cooperative Institute for Research In Environmental Sciences","NOAA":"National Oceanic and Atmospheric Administration","GSL":"Global Systems Laboratory","NSF":"National Science Foundation","NCAR":"National Center for Atmospheric Research"},"edit_url":"https://github.com/projectpythia/mpas-jedi-cookbook/blob/HEAD/README.md","thumbnail":"/mpas-jedi-cookbook/_preview/59/build/thumbnail-33e202d46f0dfc5504cf1cc6f1ea96ac.png","exports":[{"format":"md","filename":"README.md","url":"/mpas-jedi-cookbook/_preview/59/build/README-b1d6a5fb6c6f3de6e91da381e6a0c2ad.md"}]},"mdast":{"type":"root","children":[{"type":"block","children":[{"type":"image","url":"/mpas-jedi-cookbook/_preview/59/build/thumbnail-33e202d46f0dfc5504cf1cc6f1ea96ac.png","alt":"thumbnail","width":300,"key":"YaccURTOoL","urlSource":"thumbnail.png"},{"type":"paragraph","position":{"start":{"line":5,"column":1},"end":{"line":7,"column":1}},"children":[{"type":"link","url":"https://github.com/ProjectPythia/mpas-jedi-cookbook/actions/workflows/nightly-build.yaml","position":{"start":{"line":5,"column":1},"end":{"line":5,"column":1}},"children":[{"type":"image","url":"/mpas-jedi-cookbook/_preview/59/build/356de2abb8cc4cd9ce9e16cbf0c702f4.svg","alt":"nightly-build","position":{"start":{"line":5,"column":1},"end":{"line":5,"column":1}},"key":"VVsT8f5448","urlSource":"https://github.com/ProjectPythia/mpas-jedi-cookbook/actions/workflows/nightly-build.yaml/badge.svg"}],"urlSource":"https://github.com/ProjectPythia/mpas-jedi-cookbook/actions/workflows/nightly-build.yaml","error":true,"key":"A9iQclPbdu"},{"type":"text","value":"\n","position":{"start":{"line":5,"column":1},"end":{"line":5,"column":1}},"key":"wuMwP0lE5u"},{"type":"link","url":"https://binder.projectpythia.org/v2/gh/ProjectPythia/mpas-jedi-cookbook/main?labpath=notebooks","position":{"start":{"line":5,"column":1},"end":{"line":5,"column":1}},"children":[{"type":"image","url":"/mpas-jedi-cookbook/_preview/59/build/31e3f387ea168934ca949c27e9927ea4.svg","alt":"Binder","position":{"start":{"line":5,"column":1},"end":{"line":5,"column":1}},"key":"x3GHiL8IuP","urlSource":"https://binder.projectpythia.org/badge_logo.svg"}],"urlSource":"https://binder.projectpythia.org/v2/gh/ProjectPythia/mpas-jedi-cookbook/main?labpath=notebooks","key":"eJVQRivU84"},{"type":"text","value":"\n","position":{"start":{"line":5,"column":1},"end":{"line":5,"column":1}},"key":"z5MRt0ChJ3"},{"type":"cite","url":"https://doi.org/10.5281/zenodo.16797270","position":{"start":{"line":5,"column":1},"end":{"line":5,"column":1}},"children":[{"type":"image","url":"/mpas-jedi-cookbook/_preview/59/build/2653d8fad6c1905fc094f6d1470fb8a2.svg","alt":"DOI","position":{"start":{"line":5,"column":1},"end":{"line":5,"column":1}},"key":"mEizo8sHUA","urlSource":"https://zenodo.org/badge/1032750888.svg"}],"kind":"narrative","label":"https://doi.org/10.5281/zenodo.16797270","identifier":"https://doi.org/10.5281/zenodo.16797270","enumerator":"1","key":"u9fKlZBU7X"}],"key":"DP61mnTzTA"},{"type":"paragraph","position":{"start":{"line":9,"column":1},"end":{"line":9,"column":1}},"children":[{"type":"text","value":"This Project Pythia Cookbook focuses on analyzing, visualizing, and interpreting ","key":"sQJo3kJLaK"},{"type":"abbreviation","title":"Model for Prediction Across Scales","children":[{"type":"text","value":"MPAS","key":"kqGejuC281"}],"key":"gXZLYFWc3N"},{"type":"text","value":" model output on the unstructured voronoi mesh, as well as exploring ","key":"jF9Kb0BqjV"},{"type":"abbreviation","title":"Model for Prediction Across Scales","children":[{"type":"text","value":"MPAS","key":"lMoGk2rKW8"}],"key":"HfZSO6SrWA"},{"type":"text","value":"-","key":"XsN3dRyOoC"},{"type":"abbreviation","title":"Joint Effort for Data Assimilation Integration","children":[{"type":"text","value":"JEDI","key":"FrKiqQYQr6"}],"key":"aOhhPOXOHN"},{"type":"text","value":" data assimilation results in both the model and observation spaces.","key":"CfvTc1Ez1H"}],"key":"PPOmDWlOXc"},{"type":"paragraph","position":{"start":{"line":11,"column":1},"end":{"line":11,"column":1}},"children":[{"type":"strong","position":{"start":{"line":11,"column":1},"end":{"line":11,"column":1}},"children":[{"type":"text","value":"Disclaimer:","position":{"start":{"line":11,"column":1},"end":{"line":11,"column":1}},"key":"cWqAUYYZxe"}],"key":"NkR0B8ri0V"},{"type":"text","value":" This cookbook does NOT cover how to run ","key":"KokudAnz8i"},{"type":"abbreviation","title":"Model for Prediction Across Scales","children":[{"type":"text","value":"MPAS","key":"xEp5PSZo9n"}],"key":"UqqwEPmuuP"},{"type":"text","value":" or ","key":"br4fhYSoRq"},{"type":"abbreviation","title":"Joint Effort for Data Assimilation Integration","children":[{"type":"text","value":"JEDI","key":"DcJN9XQkhh"}],"key":"mnmDGVXRdH"},{"type":"text","value":". Readers are encourage to visit ","key":"s7WXltDYtx"},{"type":"link","url":"https://mpas-dev.github.io/","position":{"start":{"line":11,"column":1},"end":{"line":11,"column":1}},"children":[{"type":"text","value":"MPAS","position":{"start":{"line":11,"column":1},"end":{"line":11,"column":1}},"key":"wr7RXOR9Qz"}],"urlSource":"https://mpas-dev.github.io/","key":"PMiGtULq34"},{"type":"text","value":" or ","position":{"start":{"line":11,"column":1},"end":{"line":11,"column":1}},"key":"TmGCkHxteA"},{"type":"link","url":"https://jointcenterforsatellitedataassimilation-jedi-docs.readthedocs-hosted.com/en/latest/","position":{"start":{"line":11,"column":1},"end":{"line":11,"column":1}},"children":[{"type":"text","value":"JEDI","position":{"start":{"line":11,"column":1},"end":{"line":11,"column":1}},"key":"AwevVUdqaP"}],"urlSource":"https://jointcenterforsatellitedataassimilation-jedi-docs.readthedocs-hosted.com/en/latest/","key":"whorOEmtJd"},{"type":"text","value":" websites for more details.","position":{"start":{"line":11,"column":1},"end":{"line":11,"column":1}},"key":"MOKAxoFNSl"}],"key":"K7AvGCqUVt"},{"type":"heading","depth":2,"position":{"start":{"line":13,"column":1},"end":{"line":13,"column":1}},"children":[{"type":"text","value":"Motivation","position":{"start":{"line":13,"column":1},"end":{"line":13,"column":1}},"key":"zcUBp1eSy2"}],"identifier":"motivation","label":"Motivation","html_id":"motivation","implicit":true,"key":"gvRBoHjwtz"},{"type":"paragraph","position":{"start":{"line":15,"column":1},"end":{"line":15,"column":1}},"children":[{"type":"link","url":"https://www.noaa.gov/","position":{"start":{"line":15,"column":1},"end":{"line":15,"column":1}},"children":[{"type":"text","value":"NOAA","position":{"start":{"line":15,"column":1},"end":{"line":15,"column":1}},"key":"TNaU2h2mud"}],"urlSource":"https://www.noaa.gov/","key":"NImqOctRyD"},{"type":"text","value":"’s next generation Rapid Refresh Forecast System (","position":{"start":{"line":15,"column":1},"end":{"line":15,"column":1}},"key":"d1x5EZBmoL"},{"type":"link","url":"https://github.com/NOAA-EMC/rrfs-workflow/tree/rrfs-mpas-jedi","position":{"start":{"line":15,"column":1},"end":{"line":15,"column":1}},"children":[{"type":"text","value":"RRFS","position":{"start":{"line":15,"column":1},"end":{"line":15,"column":1}},"key":"Lcw8wRLUrH"}],"urlSource":"https://github.com/NOAA-EMC/rrfs-workflow/tree/rrfs-mpas-jedi","error":true,"key":"MXKpv9nfLF"},{"type":"text","value":") is built on the ","key":"LfUMva3NaV"},{"type":"abbreviation","title":"Model for Prediction Across Scales","children":[{"type":"text","value":"MPAS","key":"eFz7LTQPSq"}],"key":"AwWUiAPEma"},{"type":"text","value":" (Model for Prediction Accross Scals) Model and the ","key":"se7zY8NFOS"},{"type":"abbreviation","title":"Joint Effort for Data Assimilation Integration","children":[{"type":"text","value":"JEDI","key":"IoaHsgga04"}],"key":"gJ8IMf2GU4"},{"type":"text","value":" (Joint Effort for Data assimilation Integration) system. While both ","key":"Ce29hMIO34"},{"type":"abbreviation","title":"Model for Prediction Across Scales","children":[{"type":"text","value":"MPAS","key":"SKsCZg6Kqg"}],"key":"Sp6haajh03"},{"type":"text","value":" and ","key":"cgXq0gzMTL"},{"type":"abbreviation","title":"Joint Effort for Data Assimilation Integration","children":[{"type":"text","value":"JEDI","key":"nl1kIhePyK"}],"key":"dGK3cXICAv"},{"type":"text","value":" are powerful tools, they can also be complex to use and interpret. This cookbook will demonstrate how to explore ","key":"INLf4zTz0V"},{"type":"abbreviation","title":"Model for Prediction Across Scales","children":[{"type":"text","value":"MPAS","key":"ZKr8f3szwO"}],"key":"usklclKEbl"},{"type":"text","value":" output and ","key":"FFU4DYiTTB"},{"type":"abbreviation","title":"Model for Prediction Across Scales","children":[{"type":"text","value":"MPAS","key":"oXEQD1jnEG"}],"key":"s9txtDyhvx"},{"type":"text","value":"-","key":"QmppalQGNh"},{"type":"abbreviation","title":"Joint Effort for Data Assimilation Integration","children":[{"type":"text","value":"JEDI","key":"FjmFHpyASU"}],"key":"wu50D976ko"},{"type":"text","value":" analyses directly on the unstructed voronoi mesh using the ","key":"F3vbgG2e3B"},{"type":"link","url":"https://github.com/UXARRAY/uxarray","position":{"start":{"line":15,"column":1},"end":{"line":15,"column":1}},"children":[{"type":"text","value":"UXarray","position":{"start":{"line":15,"column":1},"end":{"line":15,"column":1}},"key":"WwFENIYmED"}],"urlSource":"https://github.com/UXARRAY/uxarray","error":true,"key":"gbnMA9846J"},{"type":"text","value":" package. It also includes examples for examining ","key":"HzpcSRGm5i"},{"type":"abbreviation","title":"Joint Effort for Data Assimilation Integration","children":[{"type":"text","value":"JEDI","key":"X1vreTfwKv"}],"key":"Y5mUwDxxNE"},{"type":"text","value":" analyses in observation space.","key":"Cqr9Koksb1"}],"key":"dWFUZ4KgJy"},{"type":"heading","depth":2,"position":{"start":{"line":17,"column":1},"end":{"line":17,"column":1}},"children":[{"type":"text","value":"Authors","position":{"start":{"line":17,"column":1},"end":{"line":17,"column":1}},"key":"ENcCRbzjlm"}],"identifier":"authors","label":"Authors","html_id":"authors","implicit":true,"key":"Z6lSXO5L4a"},{"type":"list","ordered":false,"spread":false,"position":{"start":{"line":19,"column":1},"end":{"line":26,"column":1}},"children":[{"type":"listItem","spread":true,"position":{"start":{"line":19,"column":1},"end":{"line":19,"column":1}},"children":[{"type":"link","url":"https://github.com/guoqing-noaa","position":{"start":{"line":19,"column":1},"end":{"line":19,"column":1}},"children":[{"type":"text","value":"Guoqing Ge (CIRES/NOAA GSL)","position":{"start":{"line":19,"column":1},"end":{"line":19,"column":1}},"key":"vaQ5B8xmcd"}],"urlSource":"https://github.com/guoqing-noaa","error":true,"key":"fScBCWS3rp"}],"key":"QxjGHQEhI3"},{"type":"listItem","spread":true,"position":{"start":{"line":20,"column":1},"end":{"line":20,"column":1}},"children":[{"type":"link","url":"https://github.com/erogluorhan","position":{"start":{"line":20,"column":1},"end":{"line":20,"column":1}},"children":[{"type":"text","value":"Orhan Eroglu (NSF NCAR)","position":{"start":{"line":20,"column":1},"end":{"line":20,"column":1}},"key":"Szff9ttqju"}],"urlSource":"https://github.com/erogluorhan","error":true,"key":"i39HSsEetj"}],"key":"GozUyDf71I"},{"type":"listItem","spread":true,"position":{"start":{"line":21,"column":1},"end":{"line":21,"column":1}},"children":[{"type":"link","url":"https://github.com/ballight42","position":{"start":{"line":21,"column":1},"end":{"line":21,"column":1}},"children":[{"type":"text","value":"Yan Pan (Duke University)","position":{"start":{"line":21,"column":1},"end":{"line":21,"column":1}},"key":"DeGEax4jWN"}],"urlSource":"https://github.com/ballight42","error":true,"key":"vfFyaH6HjA"}],"key":"ogZZExfmOF"},{"type":"listItem","spread":true,"position":{"start":{"line":22,"column":1},"end":{"line":22,"column":1}},"children":[{"type":"link","url":"https://github.com/HaidaoLin-NOAA","position":{"start":{"line":22,"column":1},"end":{"line":22,"column":1}},"children":[{"type":"text","value":"Haidao Lin (NOAA/GSL)","position":{"start":{"line":22,"column":1},"end":{"line":22,"column":1}},"key":"LntOj1TjjY"}],"urlSource":"https://github.com/HaidaoLin-NOAA","error":true,"key":"ZmrEnM3Dpu"}],"key":"k53f8PvEeb"},{"type":"listItem","spread":true,"position":{"start":{"line":23,"column":1},"end":{"line":23,"column":1}},"children":[{"type":"link","url":"https://github.com/stephen-asare","position":{"start":{"line":23,"column":1},"end":{"line":23,"column":1}},"children":[{"type":"text","value":"Stephen Asare (Florida State University)","position":{"start":{"line":23,"column":1},"end":{"line":23,"column":1}},"key":"iTAiYfFdy8"}],"urlSource":"https://github.com/stephen-asare","error":true,"key":"Ll66aWG0v5"}],"key":"wuhE11Or4U"},{"type":"listItem","spread":true,"position":{"start":{"line":24,"column":1},"end":{"line":24,"column":1}},"children":[{"type":"link","url":"https://github.com/altugkarakurt","position":{"start":{"line":24,"column":1},"end":{"line":24,"column":1}},"children":[{"type":"text","value":"Altug Karakurt (University of Colorado, Boulder)","position":{"start":{"line":24,"column":1},"end":{"line":24,"column":1}},"key":"ibD8v1Y6Yf"}],"urlSource":"https://github.com/altugkarakurt","error":true,"key":"G2di7bUj3l"}],"key":"r5WjhwGLSv"},{"type":"listItem","spread":true,"position":{"start":{"line":25,"column":1},"end":{"line":26,"column":1}},"children":[{"type":"link","url":"https://github.com/philipc2","position":{"start":{"line":25,"column":1},"end":{"line":25,"column":1}},"children":[{"type":"text","value":"Philip Chmielowiec (NSF NCAR)","position":{"start":{"line":25,"column":1},"end":{"line":25,"column":1}},"key":"H4xg26vp4O"}],"urlSource":"https://github.com/philipc2","error":true,"key":"R1LoxH11L4"}],"key":"ZDTsF5aAbc"}],"key":"HMXgjD46rY"},{"type":"heading","depth":3,"position":{"start":{"line":27,"column":1},"end":{"line":27,"column":1}},"children":[{"type":"text","value":"Contributors","position":{"start":{"line":27,"column":1},"end":{"line":27,"column":1}},"key":"TNJlBWhNG8"}],"identifier":"contributors","label":"Contributors","html_id":"contributors","implicit":true,"key":"h5w8oDce34"},{"type":"link","url":"https://github.com/ProjectPythia/mpas-jedi-cookbook/graphs/contributors","children":[{"type":"image","url":"/mpas-jedi-cookbook/_preview/59/build/09eca75402dcaac3de0c457c8d0456d5.svg","key":"kuG9V7As1v","urlSource":"https://contrib.rocks/image?repo=ProjectPythia/mpas-jedi-cookbook"}],"urlSource":"https://github.com/ProjectPythia/mpas-jedi-cookbook/graphs/contributors","error":true,"key":"EU2OKWnqZu"},{"type":"heading","depth":2,"position":{"start":{"line":33,"column":1},"end":{"line":33,"column":1}},"children":[{"type":"text","value":"Structure","position":{"start":{"line":33,"column":1},"end":{"line":33,"column":1}},"key":"fyVAyJa9AX"}],"identifier":"structure","label":"Structure","html_id":"structure","implicit":true,"key":"uZdjKElRIN"},{"type":"paragraph","position":{"start":{"line":35,"column":1},"end":{"line":35,"column":1}},"children":[{"type":"text","value":"This cookbook is broken into three sections:","position":{"start":{"line":35,"column":1},"end":{"line":35,"column":1}},"key":"TjjPBeB5qA"}],"key":"JMHf5ygEYo"},{"type":"list","ordered":false,"spread":false,"position":{"start":{"line":37,"column":1},"end":{"line":40,"column":1}},"children":[{"type":"listItem","spread":true,"position":{"start":{"line":37,"column":1},"end":{"line":37,"column":1}},"children":[{"type":"text","value":"Introduction","position":{"start":{"line":37,"column":1},"end":{"line":37,"column":1}},"key":"iuFHnLC7qB"}],"key":"cpm7w9jx5n"},{"type":"listItem","spread":true,"position":{"start":{"line":38,"column":1},"end":{"line":38,"column":1}},"children":[{"type":"abbreviation","title":"Model for Prediction Across Scales","children":[{"type":"text","value":"MPAS","key":"ITZhM83Gnk"}],"key":"juA5JefrD3"},{"type":"text","value":"(regional) Analysis and Visualization","key":"eR3vqpfc2p"}],"key":"XUcfQZgkUl"},{"type":"listItem","spread":true,"position":{"start":{"line":39,"column":1},"end":{"line":40,"column":1}},"children":[{"type":"abbreviation","title":"Joint Effort for Data Assimilation Integration","children":[{"type":"text","value":"JEDI","key":"s7Ft0hEHjM"}],"key":"rThjDZZfkG"},{"type":"text","value":"(","key":"uyyv0NGeJ9"},{"type":"abbreviation","title":"Model for Prediction Across Scales","children":[{"type":"text","value":"MPAS","key":"SOUZrqnOhg"}],"key":"epoHG05PLW"},{"type":"text","value":") Analysis and Visulization","key":"L7n3aipkFW"}],"key":"sooBPRJX26"}],"key":"FpmG84ezsQ"},{"type":"heading","depth":3,"position":{"start":{"line":41,"column":1},"end":{"line":41,"column":1}},"children":[{"type":"text","value":"Section 1. Introduction","position":{"start":{"line":41,"column":1},"end":{"line":41,"column":1}},"key":"Kxt3OOvlZB"}],"identifier":"section-1-introduction","label":"Section 1. Introduction","html_id":"section-1-introduction","implicit":true,"key":"ZcVV1GGtH0"},{"type":"paragraph","position":{"start":{"line":43,"column":1},"end":{"line":43,"column":1}},"children":[{"type":"text","value":"The introduction part will provide a quick overview about ","key":"uzwtpx1soA"},{"type":"abbreviation","title":"Model for Prediction Across Scales","children":[{"type":"text","value":"MPAS","key":"yrZItXMA8P"}],"key":"FQBnbqUxJK"},{"type":"text","value":", ","key":"LstbaeSHrM"},{"type":"abbreviation","title":"Joint Effort for Data Assimilation Integration","children":[{"type":"text","value":"JEDI","key":"Mh9LSQoGPF"}],"key":"jI7ysFD2ur"},{"type":"text","value":" and ","key":"LwssLWpZ99"},{"type":"abbreviation","title":"Rapid Refresh Forecast System","children":[{"type":"text","value":"RRFS","key":"d2fGSqDNKW"}],"key":"UGfNJpRTsm"},{"type":"text","value":"(v2).","key":"q8spYNiGQR"}],"key":"tJJJvlEI3P"},{"type":"heading","depth":3,"position":{"start":{"line":45,"column":1},"end":{"line":45,"column":1}},"children":[{"type":"text","value":"Section 2. ","key":"LXEBTDRCTw"},{"type":"abbreviation","title":"Model for Prediction Across Scales","children":[{"type":"text","value":"MPAS","key":"c94qtBqfiQ"}],"key":"tBjVhyhuUd"},{"type":"text","value":" (regional) Analysis and Visualization","key":"DbqdU4ch41"}],"identifier":"section-2-mpas-regional-analysis-and-visualization","label":"Section 2. MPAS (regional) Analysis and Visualization","html_id":"section-2-mpas-regional-analysis-and-visualization","implicit":true,"key":"PTNpkIfdZr"},{"type":"paragraph","position":{"start":{"line":47,"column":1},"end":{"line":47,"column":1}},"children":[{"type":"text","value":"This part will demonstrate how to make basic and advanced ","key":"DPmB7jwUuG"},{"type":"abbreviation","title":"Model for Prediction Across Scales","children":[{"type":"text","value":"MPAS","key":"q9aclXFRjC"}],"key":"Ec7WCJU6US"},{"type":"text","value":" analysis and visulazation using UXarray.","key":"oChdb2w4wz"}],"key":"ecdG0MRyiG"},{"type":"heading","depth":3,"position":{"start":{"line":49,"column":1},"end":{"line":49,"column":1}},"children":[{"type":"text","value":"Section 3. ","key":"x2eE09jOvI"},{"type":"abbreviation","title":"Model for Prediction Across Scales","children":[{"type":"text","value":"MPAS","key":"Npimk1Loq4"}],"key":"p6Xp9S2XW6"},{"type":"text","value":"-","key":"Irh1YRPWbL"},{"type":"abbreviation","title":"Joint Effort for Data Assimilation Integration","children":[{"type":"text","value":"JEDI","key":"RJKUno2Nj0"}],"key":"KCnARMPqzk"},{"type":"text","value":" Analysis and Visualization","key":"c6CGTOhy5h"}],"identifier":"section-3-mpas-jedi-analysis-and-visualization","label":"Section 3. MPAS-JEDI Analysis and Visualization","html_id":"section-3-mpas-jedi-analysis-and-visualization","implicit":true,"key":"XRxf8aImxf"},{"type":"paragraph","position":{"start":{"line":51,"column":1},"end":{"line":51,"column":1}},"children":[{"type":"text","value":"This part will demonstrate how to explore ","key":"fgAtu2FuNj"},{"type":"abbreviation","title":"Model for Prediction Across Scales","children":[{"type":"text","value":"MPAS","key":"IB5PLF8fLQ"}],"key":"momvdAtqdC"},{"type":"text","value":"-","key":"xNLp7B7rRc"},{"type":"abbreviation","title":"Joint Effort for Data Assimilation Integration","children":[{"type":"text","value":"JEDI","key":"Qhr8yjNOSL"}],"key":"TSyNajO16d"},{"type":"text","value":" data assimilation results in both the model and observation spaces.","key":"kS2h7dsk1Z"}],"key":"JaZHbkJtmF"},{"type":"heading","depth":2,"position":{"start":{"line":53,"column":1},"end":{"line":53,"column":1}},"children":[{"type":"text","value":"Running the Notebooks","position":{"start":{"line":53,"column":1},"end":{"line":53,"column":1}},"key":"li9ZZxPzMA"}],"identifier":"running-the-notebooks","label":"Running the Notebooks","html_id":"running-the-notebooks","implicit":true,"key":"YZNGPkUAXr"},{"type":"paragraph","position":{"start":{"line":55,"column":1},"end":{"line":55,"column":1}},"children":[{"type":"text","value":"You can either run the notebook using ","position":{"start":{"line":55,"column":1},"end":{"line":55,"column":1}},"key":"ZfZWcdocw0"},{"type":"link","url":"https://binder.projectpythia.org/","position":{"start":{"line":55,"column":1},"end":{"line":55,"column":1}},"children":[{"type":"text","value":"Binder","position":{"start":{"line":55,"column":1},"end":{"line":55,"column":1}},"key":"x36tMCjXYE"}],"urlSource":"https://binder.projectpythia.org/","key":"IVXigLYe4C"},{"type":"text","value":" or on your local machine.","position":{"start":{"line":55,"column":1},"end":{"line":55,"column":1}},"key":"YOQyUaSlUY"}],"key":"kncVljka7j"},{"type":"heading","depth":3,"position":{"start":{"line":57,"column":1},"end":{"line":57,"column":1}},"children":[{"type":"text","value":"Running on Binder","position":{"start":{"line":57,"column":1},"end":{"line":57,"column":1}},"key":"h4dXuiqy6n"}],"identifier":"running-on-binder","label":"Running on Binder","html_id":"running-on-binder","implicit":true,"key":"qVZInfsXOr"},{"type":"paragraph","position":{"start":{"line":59,"column":1},"end":{"line":59,"column":1}},"children":[{"type":"text","value":"The simplest way to interact with a Jupyter Notebook is through ","position":{"start":{"line":59,"column":1},"end":{"line":59,"column":1}},"key":"W3IBPJRft5"},{"type":"link","url":"https://binder.projectpythia.org/","position":{"start":{"line":59,"column":1},"end":{"line":59,"column":1}},"children":[{"type":"text","value":"Binder","position":{"start":{"line":59,"column":1},"end":{"line":59,"column":1}},"key":"rIHoxgDX3S"}],"urlSource":"https://binder.projectpythia.org/","key":"JtDvySGxNp"},{"type":"text","value":", which enables the execution of a ","position":{"start":{"line":59,"column":1},"end":{"line":59,"column":1}},"key":"QNZZ1k0WDJ"},{"type":"link","url":"https://jupyterbook.org","position":{"start":{"line":59,"column":1},"end":{"line":59,"column":1}},"children":[{"type":"text","value":"Jupyter Book","position":{"start":{"line":59,"column":1},"end":{"line":59,"column":1}},"key":"Y33n8i1Xyg"}],"urlSource":"https://jupyterbook.org","key":"Uz3cfqQDPL"},{"type":"text","value":" in the cloud. All you need to know is how to launch a Pythia Cookbooks chapter via Binder. Simply navigate your mouse to the top right corner of the book chapter you are viewing and click on the rocket ship icon, and be sure to select “launch Binder”. After a moment you should be presented with a notebook that you can interact with. I.e. you’ll be able to execute and even change the example programs. You’ll see that the code cells have no output at first, until you execute them by pressing ","position":{"start":{"line":59,"column":1},"end":{"line":59,"column":1}},"key":"zf45qKZIFj"},{"type":"keyboard","children":[{"type":"text","value":"Shift","key":"hteYosabL7"}],"key":"AwKQ4homZs"},{"type":"text","value":"+","position":{"start":{"line":59,"column":1},"end":{"line":59,"column":1}},"key":"ttNlbZMofZ"},{"type":"keyboard","children":[{"type":"text","value":"Enter","key":"tCNi91bKyY"}],"key":"bMJ5Hgsh4t"},{"type":"text","value":". Complete details on how to interact with a live Jupyter notebook are described in ","position":{"start":{"line":59,"column":1},"end":{"line":59,"column":1}},"key":"K30NekfoYU"},{"type":"link","url":"https://foundations.projectpythia.org/foundations/getting-started-jupyter.html","position":{"start":{"line":59,"column":1},"end":{"line":59,"column":1}},"children":[{"type":"text","value":"Getting Started with Jupyter","position":{"start":{"line":59,"column":1},"end":{"line":59,"column":1}},"key":"nyMQWL7C80"}],"urlSource":"https://foundations.projectpythia.org/foundations/getting-started-jupyter.html","key":"XJZRuXrev0"},{"type":"text","value":".","position":{"start":{"line":59,"column":1},"end":{"line":59,"column":1}},"key":"t8pw75AK3U"}],"key":"jFTTbHHEXj"},{"type":"paragraph","position":{"start":{"line":61,"column":1},"end":{"line":61,"column":1}},"children":[{"type":"text","value":"Note, not all Cookbook chapters are executable. If you do not see the rocket ship icon, such as on this page, you are not viewing an executable book chapter.","position":{"start":{"line":61,"column":1},"end":{"line":61,"column":1}},"key":"facLtjlRkZ"}],"key":"XCf5jhJ0ej"},{"type":"heading","depth":3,"position":{"start":{"line":63,"column":1},"end":{"line":63,"column":1}},"children":[{"type":"text","value":"Running on Your Own Machine","position":{"start":{"line":63,"column":1},"end":{"line":63,"column":1}},"key":"LvYB1GAhT8"}],"identifier":"running-on-your-own-machine","label":"Running on Your Own Machine","html_id":"running-on-your-own-machine","implicit":true,"key":"Pafvvn1qOu"},{"type":"paragraph","position":{"start":{"line":65,"column":1},"end":{"line":65,"column":1}},"children":[{"type":"text","value":"If you are interested in running this material locally on your computer, you will need to follow this workflow:","position":{"start":{"line":65,"column":1},"end":{"line":65,"column":1}},"key":"Q6FyqGMYpJ"}],"key":"utTs4GmayP"},{"type":"list","ordered":true,"start":1,"spread":false,"position":{"start":{"line":67,"column":1},"end":{"line":91,"column":1}},"children":[{"type":"listItem","spread":true,"position":{"start":{"line":67,"column":1},"end":{"line":72,"column":1}},"children":[{"type":"paragraph","position":{"start":{"line":67,"column":1},"end":{"line":67,"column":1}},"children":[{"type":"text","value":"Clone the ","position":{"start":{"line":67,"column":1},"end":{"line":67,"column":1}},"key":"HTD0YySLze"},{"type":"inlineCode","value":"https://github.com/ProjectPythia/mpas-jedi-cookbook","position":{"start":{"line":67,"column":1},"end":{"line":67,"column":1}},"key":"RwAbGDkHXs"},{"type":"text","value":" repository:","position":{"start":{"line":67,"column":1},"end":{"line":67,"column":1}},"key":"D1ErSwzZbC"}],"key":"Bj7HmFeeg9"},{"type":"code","lang":"bash","value":" git clone https://github.com/ProjectPythia/mpas-jedi-cookbook","position":{"start":{"line":69,"column":1},"end":{"line":71,"column":1}},"key":"Kzq76EI5fV"}],"key":"kQrbLEveL2"},{"type":"listItem","spread":true,"position":{"start":{"line":73,"column":1},"end":{"line":78,"column":1}},"children":[{"type":"paragraph","position":{"start":{"line":73,"column":1},"end":{"line":73,"column":1}},"children":[{"type":"text","value":"Move into the ","position":{"start":{"line":73,"column":1},"end":{"line":73,"column":1}},"key":"W6CaNxIKbT"},{"type":"inlineCode","value":"mpas-jedi-cookbook","position":{"start":{"line":73,"column":1},"end":{"line":73,"column":1}},"key":"x26CVtuy8w"},{"type":"text","value":" directory","position":{"start":{"line":73,"column":1},"end":{"line":73,"column":1}},"key":"dQPhtlearS"}],"key":"b3z9SbJRYj"},{"type":"code","lang":"bash","value":"cd mpas-jedi-cookbook","position":{"start":{"line":75,"column":1},"end":{"line":77,"column":1}},"key":"IszpOQCscT"}],"key":"t0SmkYdNPK"},{"type":"listItem","spread":true,"position":{"start":{"line":79,"column":1},"end":{"line":85,"column":1}},"children":[{"type":"paragraph","position":{"start":{"line":79,"column":1},"end":{"line":79,"column":1}},"children":[{"type":"text","value":"Create and activate your conda environment from the ","position":{"start":{"line":79,"column":1},"end":{"line":79,"column":1}},"key":"d4BhvY2OaH"},{"type":"inlineCode","value":"environment.yml","position":{"start":{"line":79,"column":1},"end":{"line":79,"column":1}},"key":"qRVQAkfSz4"},{"type":"text","value":" file","position":{"start":{"line":79,"column":1},"end":{"line":79,"column":1}},"key":"K3dsqsdtof"}],"key":"XQ6V6S8Ybr"},{"type":"code","lang":"bash","value":"conda env create -f environment.yml\nconda activate mpas-jedi-cookbook","position":{"start":{"line":81,"column":1},"end":{"line":84,"column":1}},"key":"zhE0ojO9fN"}],"key":"LakNrgeiul"},{"type":"listItem","spread":true,"position":{"start":{"line":86,"column":1},"end":{"line":91,"column":1}},"children":[{"type":"paragraph","position":{"start":{"line":86,"column":1},"end":{"line":86,"column":1}},"children":[{"type":"text","value":"Move into the ","position":{"start":{"line":86,"column":1},"end":{"line":86,"column":1}},"key":"HKXQQ1eJIs"},{"type":"inlineCode","value":"notebooks","position":{"start":{"line":86,"column":1},"end":{"line":86,"column":1}},"key":"ldbQSRtv3y"},{"type":"text","value":" directory and start up Jupyterlab","position":{"start":{"line":86,"column":1},"end":{"line":86,"column":1}},"key":"WsHLPeEmtY"}],"key":"aF74Pduqml"},{"type":"code","lang":"bash","value":"cd notebooks/\njupyter lab","position":{"start":{"line":88,"column":1},"end":{"line":91,"column":1}},"key":"kYs5Kh2JnG"}],"key":"oVMnEdkEZi"}],"key":"V8aVqgmfEX"}],"key":"XEbuc0uQI0"}],"key":"LxXXSwOHPb"},"references":{"cite":{"order":["https://doi.org/10.5281/zenodo.16797270"],"data":{"https://doi.org/10.5281/zenodo.16797270":{"label":"https://doi.org/10.5281/zenodo.16797270","enumerator":"1","doi":"10.5281/ZENODO.16797270","html":"Ge, G., Eroglu, O., Stephen, A., Pan, Y., Karakurt, A., Lin, H., & mpas-jedi-cookbook contributors. (2025). <i>MPAS+JEDI Cookbook</i>. Zenodo. <a target=\"_blank\" rel=\"noreferrer\" href=\"https://doi.org/10.5281/ZENODO.16797270\">10.5281/ZENODO.16797270</a>","url":"https://doi.org/10.5281/ZENODO.16797270"}}}},"footer":{"navigation":{"next":{"title":"How to Cite This Cookbook","url":"/notebooks/how-to-cite","group":"Preamble"}}},"domain":"http://localhost:3000"}