{"version":2,"kind":"Notebook","sha256":"59377cc440fd53a658573610066ac17d0e13cfbece50940b3dec71065236aa5f","slug":"notebooks.overview-rrfsv2","location":"/notebooks/overview-rrfsv2.ipynb","dependencies":[],"frontmatter":{"title":"RRFSv2 Overview","content_includes_title":false,"kernelspec":{"name":"python3","display_name":"Python 3 (ipykernel)","language":"python"},"authors":[{"nameParsed":{"literal":"Guoqing Ge","given":"Guoqing","family":"Ge"},"name":"Guoqing Ge","id":"contributors-myst-generated-uid-0"},{"nameParsed":{"literal":"Orhan Eroglu","given":"Orhan","family":"Eroglu"},"name":"Orhan Eroglu","id":"contributors-myst-generated-uid-1"},{"nameParsed":{"literal":"Yan Pan","given":"Yan","family":"Pan"},"name":"Yan Pan","id":"contributors-myst-generated-uid-2"},{"nameParsed":{"literal":"Haidao Lin","given":"Haidao","family":"Lin"},"name":"Haidao Lin","id":"contributors-myst-generated-uid-3"},{"nameParsed":{"literal":"Stephen Asare","given":"Stephen","family":"Asare"},"name":"Stephen Asare","id":"contributors-myst-generated-uid-4"},{"nameParsed":{"literal":"Altug Karakurt","given":"Altug","family":"Karakurt"},"name":"Altug Karakurt","id":"contributors-myst-generated-uid-5"},{"nameParsed":{"literal":"Philip Chmielowiec","given":"Philip","family":"Chmielowiec"},"name":"Philip Chmielowiec","id":"contributors-myst-generated-uid-6"}],"open_access":true,"license":{"content":{"id":"CC-BY-4.0","url":"https://creativecommons.org/licenses/by/4.0/","name":"Creative Commons Attribution 4.0 International","free":true,"CC":true},"code":{"id":"Apache-2.0","url":"https://opensource.org/licenses/Apache-2.0","name":"Apache License 2.0","free":true,"osi":true}},"github":"https://github.com/projectpythia/mpas-jedi-cookbook","copyright":"2025","affiliations":[{"id":"UAlbany","name":"University at Albany (SUNY)","department":"Atmospheric and Environmental Sciences","url":"https://www.albany.edu/daes"},{"id":"CISL","name":"NSF National Center for Atmospheric Research","department":"Computational and Information Systems Lab","url":"https://www.cisl.ucar.edu"},{"id":"Unidata","name":"NSF Unidata","url":"https://www.unidata.ucar.edu"},{"id":"Argonne","name":"Argonne National Laboratory","department":"Environmental Science Division","url":"https://www.anl.gov/evs"},{"id":"CarbonPlan","name":"CarbonPlan","url":"https://carbonplan.org"},{"id":"NVIDIA","name":"NVIDIA Corporation","url":"https://www.nvidia.com/"}],"abbreviations":{"MPAS":"Model for Prediction Across Scales","JEDI":"Joint Effort for Data Assimilation Integration","RRFS":"Rapid Refresh Forecast System","DA":"Data Assimilation","CIRES":"Cooperative Institute for Research In Environmental Sciences","NOAA":"National Oceanic and Atmospheric Administration","GSL":"Global Systems Laboratory","NSF":"National Science Foundation","NCAR":"National Center for Atmospheric Research"},"numbering":{"title":{"offset":1}},"source_url":"https://github.com/projectpythia/mpas-jedi-cookbook/blob/HEAD/notebooks/overview-rrfsv2.ipynb","edit_url":"https://github.com/projectpythia/mpas-jedi-cookbook/edit/HEAD/notebooks/overview-rrfsv2.ipynb","thumbnail":"/mpas-jedi-cookbook/_preview/66/build/rrfsv2-5f9f434f1b00a927a4df6743557657d4.png","exports":[{"format":"ipynb","filename":"overview-rrfsv2.ipynb","url":"/mpas-jedi-cookbook/_preview/66/build/overview-rrfsv2-6cca48012f2448285431c67949f9e4d6.ipynb"}]},"widgets":{},"mdast":{"type":"root","children":[{"type":"block","kind":"notebook-content","children":[{"type":"image","url":"/mpas-jedi-cookbook/_preview/66/build/rrfsv2-5f9f434f1b00a927a4df6743557657d4.png","alt":"RRFSv2","width":"400px","align":"center","key":"YDq7t8k3FK","urlSource":"images/rrfsv2.png"},{"type":"heading","depth":2,"position":{"start":{"line":7,"column":1},"end":{"line":7,"column":1}},"children":[{"type":"text","value":"In this section, you’ll learn:","position":{"start":{"line":7,"column":1},"end":{"line":7,"column":1}},"key":"AuH3crubcE"}],"identifier":"in-this-section-youll-learn","label":"In this section, you’ll learn:","html_id":"in-this-section-youll-learn","implicit":true,"key":"DPXsZK9pre"},{"type":"list","ordered":false,"spread":false,"position":{"start":{"line":9,"column":1},"end":{"line":12,"column":1}},"children":[{"type":"listItem","spread":true,"position":{"start":{"line":9,"column":1},"end":{"line":9,"column":1}},"children":[{"type":"paragraph","children":[{"type":"text","value":"What’s ","key":"C4WyfYUVUZ"},{"type":"abbreviation","title":"Rapid Refresh Forecast System","children":[{"type":"text","value":"RRFS","key":"VxXVwv7JS1"}],"key":"YcftJPzJbq"},{"type":"text","value":"(v2)?","key":"fAqEBeILgY"}],"key":"EmZ2PgTdkA"}],"key":"J3jZpaKO60"},{"type":"listItem","spread":true,"position":{"start":{"line":10,"column":1},"end":{"line":10,"column":1}},"children":[{"type":"paragraph","children":[{"type":"text","value":"What’s R","key":"aOrBKVFYrf"},{"type":"abbreviation","title":"Data Assimilation","children":[{"type":"text","value":"DA","key":"xJE6MmOi4a"}],"key":"NvfSQVUTxW"},{"type":"text","value":"SApp?","key":"d4XY8Hb317"}],"key":"RzxowYhKTm"}],"key":"bfdIUNjwKe"},{"type":"listItem","spread":true,"position":{"start":{"line":11,"column":1},"end":{"line":12,"column":1}},"children":[{"type":"paragraph","children":[{"type":"text","value":"What’s rrfs-workflow?","position":{"start":{"line":11,"column":1},"end":{"line":11,"column":1}},"key":"EN2xptrRo3"}],"key":"MdFu91QdrU"}],"key":"SEr2kxdZj9"}],"key":"lbdxfyuO1Z"},{"type":"heading","depth":2,"position":{"start":{"line":13,"column":1},"end":{"line":13,"column":1}},"children":[{"type":"text","value":"Related Documentation","position":{"start":{"line":13,"column":1},"end":{"line":13,"column":1}},"key":"MHneE6YMBY"}],"identifier":"related-documentation","label":"Related Documentation","html_id":"related-documentation","implicit":true,"key":"mhXLICR7yL"},{"type":"list","ordered":false,"spread":false,"position":{"start":{"line":15,"column":1},"end":{"line":18,"column":1}},"children":[{"type":"listItem","spread":true,"position":{"start":{"line":15,"column":1},"end":{"line":15,"column":1}},"children":[{"type":"paragraph","children":[{"type":"link","url":"https://github.com/NOAA-EMC/rrfs-workflow","position":{"start":{"line":15,"column":1},"end":{"line":15,"column":1}},"children":[{"type":"text","value":"rrfs-workflow","position":{"start":{"line":15,"column":1},"end":{"line":15,"column":1}},"key":"lOuag4L4I3"}],"urlSource":"https://github.com/NOAA-EMC/rrfs-workflow","error":true,"key":"fNuJilrpxn"}],"key":"puhSnDpgZh"}],"key":"THkxWVVbbr"},{"type":"listItem","spread":true,"position":{"start":{"line":16,"column":1},"end":{"line":16,"column":1}},"children":[{"type":"paragraph","children":[{"type":"link","url":"https://github.com/NOAA-EMC/RDASApp","position":{"start":{"line":16,"column":1},"end":{"line":16,"column":1}},"children":[{"type":"text","value":"RDASApp","position":{"start":{"line":16,"column":1},"end":{"line":16,"column":1}},"key":"fkbtXUMo3t"}],"urlSource":"https://github.com/NOAA-EMC/RDASApp","error":true,"key":"nCVCRxVOe6"}],"key":"SCQgeZe1GG"}],"key":"tK1k4eDbPV"},{"type":"listItem","spread":true,"position":{"start":{"line":17,"column":1},"end":{"line":18,"column":1}},"children":[{"type":"paragraph","children":[{"type":"link","url":"https://docs.google.com/presentation/d/1HPx2LzX8Hf9Imztl4OpyXdyTTWoN4hBOId4AP7bhyYM/edit?slide=id.g330660abd74_0_6#slide=id.g330660abd74_0_6","position":{"start":{"line":17,"column":1},"end":{"line":17,"column":1}},"children":[{"type":"text","value":"rrfs-workflow in depth (slides)","position":{"start":{"line":17,"column":1},"end":{"line":17,"column":1}},"key":"mmpLMQPJ7H"}],"urlSource":"https://docs.google.com/presentation/d/1HPx2LzX8Hf9Imztl4OpyXdyTTWoN4hBOId4AP7bhyYM/edit?slide=id.g330660abd74_0_6#slide=id.g330660abd74_0_6","key":"rFzKDE5dCv"},{"type":"text","value":"(request access if you are not able to view the slides)","position":{"start":{"line":17,"column":1},"end":{"line":17,"column":1}},"key":"JaaEA8ROW6"}],"key":"YYlM0YndqE"}],"key":"KVtj7D4hUt"}],"key":"vFIM1UT7GE"},{"type":"heading","depth":2,"position":{"start":{"line":19,"column":1},"end":{"line":19,"column":1}},"children":[{"type":"text","value":"Prerequisites","position":{"start":{"line":19,"column":1},"end":{"line":19,"column":1}},"key":"rukWxeJAJK"}],"identifier":"prerequisites","label":"Prerequisites","html_id":"prerequisites","implicit":true,"key":"d60gpq7kTT"},{"type":"table","position":{"start":{"line":21,"column":1},"end":{"line":24,"column":1}},"children":[{"type":"tableRow","position":{"start":{"line":21,"column":1},"end":{"line":21,"column":1}},"children":[{"type":"tableCell","header":true,"position":{"start":{"line":21,"column":1},"end":{"line":21,"column":1}},"children":[{"type":"text","value":"Concepts","position":{"start":{"line":21,"column":1},"end":{"line":21,"column":1}},"key":"pFcMH4hFOS"}],"key":"VCjIZLRgc0"},{"type":"tableCell","header":true,"position":{"start":{"line":21,"column":1},"end":{"line":21,"column":1}},"children":[{"type":"text","value":"Importance","position":{"start":{"line":21,"column":1},"end":{"line":21,"column":1}},"key":"IibhiisWWf"}],"key":"ZkwkpBa07u"},{"type":"tableCell","header":true,"position":{"start":{"line":21,"column":1},"end":{"line":21,"column":1}},"children":[{"type":"text","value":"Notes","position":{"start":{"line":21,"column":1},"end":{"line":21,"column":1}},"key":"DOz2kOo0AH"}],"key":"id3l2wYDUZ"}],"key":"OnVcMlqidN"},{"type":"tableRow","position":{"start":{"line":23,"column":1},"end":{"line":23,"column":1}},"children":[{"type":"tableCell","position":{"start":{"line":23,"column":1},"end":{"line":23,"column":1}},"children":[{"type":"text","value":"data assimilation","position":{"start":{"line":23,"column":1},"end":{"line":23,"column":1}},"key":"g9JYjF9huG"}],"key":"pycZ4Z5Vib"},{"type":"tableCell","position":{"start":{"line":23,"column":1},"end":{"line":23,"column":1}},"children":[{"type":"text","value":"Helpful","position":{"start":{"line":23,"column":1},"end":{"line":23,"column":1}},"key":"AgVTt5Y2t9"}],"key":"kUPt5LG6GN"},{"type":"tableCell","position":{"start":{"line":23,"column":1},"end":{"line":23,"column":1}},"children":[],"key":"PbPGneaJb2"}],"key":"HXwXQllma0"},{"type":"tableRow","position":{"start":{"line":24,"column":1},"end":{"line":24,"column":1}},"children":[{"type":"tableCell","position":{"start":{"line":24,"column":1},"end":{"line":24,"column":1}},"children":[{"type":"text","value":"Research to Operation","position":{"start":{"line":24,"column":1},"end":{"line":24,"column":1}},"key":"KkGIZdiR1f"}],"key":"O5GCx5GsaV"},{"type":"tableCell","position":{"start":{"line":24,"column":1},"end":{"line":24,"column":1}},"children":[{"type":"text","value":"Helpful","position":{"start":{"line":24,"column":1},"end":{"line":24,"column":1}},"key":"yJUO6Mdo9X"}],"key":"WeeKCaurMM"},{"type":"tableCell","position":{"start":{"line":24,"column":1},"end":{"line":24,"column":1}},"children":[],"key":"zURoks5oom"}],"key":"KoFRQjCNcE"}],"key":"fuvDS9uFa9"},{"type":"paragraph","position":{"start":{"line":26,"column":1},"end":{"line":26,"column":1}},"children":[{"type":"strong","position":{"start":{"line":26,"column":1},"end":{"line":26,"column":1}},"children":[{"type":"text","value":"Time to learn","position":{"start":{"line":26,"column":1},"end":{"line":26,"column":1}},"key":"oJRhgZtcjL"}],"key":"ZeVeMOpgcf"},{"type":"text","value":": 5 minutes","position":{"start":{"line":26,"column":1},"end":{"line":26,"column":1}},"key":"soTPvDdO0q"}],"key":"thoDhsqGYo"},{"type":"thematicBreak","position":{"start":{"line":28,"column":1},"end":{"line":28,"column":1}},"key":"Ha3qkeUOPz"}],"key":"ZCVSLS1cch"},{"type":"block","kind":"notebook-content","children":[{"type":"paragraph","position":{"start":{"line":1,"column":1},"end":{"line":1,"column":1}},"children":[{"type":"abbreviation","title":"National Oceanic and Atmospheric Administration","children":[{"type":"text","value":"NOAA","key":"DsEs5dzgFU"}],"key":"G9624hNXIz"},{"type":"text","value":" has been developing the Rapid Refresh Forecast System (","key":"P8rMotxIyN"},{"type":"abbreviation","title":"Rapid Refresh Forecast System","children":[{"type":"text","value":"RRFS","key":"svddf5qnzW"}],"key":"kSMxm2GZ3M"},{"type":"text","value":") to provide high-resolution, rapidly updating weather forecasts. The first version of ","key":"Q2ATMYgfIA"},{"type":"abbreviation","title":"Rapid Refresh Forecast System","children":[{"type":"text","value":"RRFS","key":"uc3Xx8iNgG"}],"key":"WmwIHDWGdX"},{"type":"text","value":" is built on ","key":"vbTaojsYYa"},{"type":"link","url":"https://www.gfdl.noaa.gov/fv3/","position":{"start":{"line":1,"column":1},"end":{"line":1,"column":1}},"children":[{"type":"text","value":"the FV3 model","position":{"start":{"line":1,"column":1},"end":{"line":1,"column":1}},"key":"DtE7HGtqQX"}],"urlSource":"https://www.gfdl.noaa.gov/fv3/","key":"DQAk8Vuz8P"},{"type":"text","value":") and the Gridpoint Statistical Interpolation (GSI) data assimilation system (","position":{"start":{"line":1,"column":1},"end":{"line":1,"column":1}},"key":"tVuhjvf9F0"},{"type":"link","url":"https://dtcenter.org/sites/default/files/GSIUserGuide_v3.7_0.pdf","position":{"start":{"line":1,"column":1},"end":{"line":1,"column":1}},"children":[{"type":"text","value":"GSI info","position":{"start":{"line":1,"column":1},"end":{"line":1,"column":1}},"key":"ITTZMn08Up"}],"urlSource":"https://dtcenter.org/sites/default/files/GSIUserGuide_v3.7_0.pdf","key":"YN2jJPOImU"},{"type":"text","value":"). The next-generation ","key":"AKzx9qlCyt"},{"type":"abbreviation","title":"Rapid Refresh Forecast System","children":[{"type":"text","value":"RRFS","key":"t7OHtlGXIH"}],"key":"F7AKAbVhK9"},{"type":"text","value":", known as ","key":"kzXCmC9zTP"},{"type":"abbreviation","title":"Rapid Refresh Forecast System","children":[{"type":"text","value":"RRFS","key":"CuKmcRjVRA"}],"key":"kqFXnwRp0g"},{"type":"text","value":"v2, adopts the ","key":"Dk0MDt4YbA"},{"type":"abbreviation","title":"Model for Prediction Across Scales","children":[{"type":"text","value":"MPAS","key":"QQF99dFVz8"}],"key":"NrnBkGM6oQ"},{"type":"text","value":" model and the ","key":"FQUcJa5AY3"},{"type":"abbreviation","title":"Joint Effort for Data Assimilation Integration","children":[{"type":"text","value":"JEDI","key":"mXaIxiX115"}],"key":"GZQUOokdRr"},{"type":"text","value":" data assimilation framework. Development of ","key":"DUV5kUS2eR"},{"type":"abbreviation","title":"Rapid Refresh Forecast System","children":[{"type":"text","value":"RRFS","key":"tjjXQoyYWI"}],"key":"Mge5pzEFAJ"},{"type":"text","value":"v2 is a collaborative effort between ","key":"WNJ3zvQD4W"},{"type":"abbreviation","title":"National Oceanic and Atmospheric Administration","children":[{"type":"text","value":"NOAA","key":"frg6fLWXDq"}],"key":"yf0uP5Reao"},{"type":"text","value":"’s Global Systems Laboratory (","key":"VpEgo4vUl8"},{"type":"link","url":"https://gsl.noaa.gov/","position":{"start":{"line":1,"column":1},"end":{"line":1,"column":1}},"children":[{"type":"text","value":"GSL","position":{"start":{"line":1,"column":1},"end":{"line":1,"column":1}},"key":"lYzBnAyOEy"}],"urlSource":"https://gsl.noaa.gov/","key":"OtIM7f0dEJ"},{"type":"text","value":") and ","key":"aHAsTHx5Uf"},{"type":"abbreviation","title":"National Oceanic and Atmospheric Administration","children":[{"type":"text","value":"NOAA","key":"i5JXLfiEu3"}],"key":"MyBJzgynYA"},{"type":"text","value":"’s Environmental Modeling Center (","key":"N9VdNRLtJX"},{"type":"link","url":"https://www.emc.ncep.noaa.gov/emc.php","position":{"start":{"line":1,"column":1},"end":{"line":1,"column":1}},"children":[{"type":"text","value":"EMC","position":{"start":{"line":1,"column":1},"end":{"line":1,"column":1}},"key":"t6I5sjBJlZ"}],"urlSource":"https://www.emc.ncep.noaa.gov/emc.php","key":"Ip6a3BYNf8"},{"type":"text","value":"), with the goal of operational deployment around 2028 or 2029.","position":{"start":{"line":1,"column":1},"end":{"line":1,"column":1}},"key":"mQgRXqoW68"}],"key":"PmEURQckaf"},{"type":"paragraph","position":{"start":{"line":3,"column":1},"end":{"line":3,"column":1}},"children":[{"type":"abbreviation","title":"Rapid Refresh Forecast System","children":[{"type":"text","value":"RRFS","key":"U9AyEdStXk"}],"key":"UbCmkD4VyZ"},{"type":"text","value":"v2 convers a regional domain with a special resolution of around 3km. The ","key":"OnvQLEqmdY"},{"type":"abbreviation","title":"Model for Prediction Across Scales","children":[{"type":"text","value":"MPAS","key":"pvMjq3VQfL"}],"key":"ua84fupkXz"},{"type":"text","value":" model has being enhanced with ","key":"gRvHR8kzYB"},{"type":"abbreviation","title":"Global Systems Laboratory","children":[{"type":"text","value":"GSL","key":"MD9fH5KdiS"}],"key":"mPZCdw4Cwd"},{"type":"text","value":"/UFS physics (","key":"dspUFPr0BZ"},{"type":"link","url":"https://github.com/ufs-community/MPAS-Model","position":{"start":{"line":3,"column":1},"end":{"line":3,"column":1}},"children":[{"type":"text","value":"link to the UFS MPAS","position":{"start":{"line":3,"column":1},"end":{"line":3,"column":1}},"key":"Tjoiu4l02f"}],"urlSource":"https://github.com/ufs-community/MPAS-Model","error":true,"key":"fMJx5qU7RW"},{"type":"text","value":") to improve forecast performance. To support ","key":"hbWsL2ifnw"},{"type":"abbreviation","title":"Rapid Refresh Forecast System","children":[{"type":"text","value":"RRFS","key":"F0zaL0WOpN"}],"key":"VIM6LImzy8"},{"type":"text","value":"v2’s unique requirements, a specialized proxy application—","key":"YjSpSlCRyC"},{"type":"link","url":"https://github.com/NOAA-EMC/RDASApp/","position":{"start":{"line":3,"column":1},"end":{"line":3,"column":1}},"children":[{"type":"text","value":"RDASApp","position":{"start":{"line":3,"column":1},"end":{"line":3,"column":1}},"key":"eqRRZf1LWT"}],"urlSource":"https://github.com/NOAA-EMC/RDASApp/","error":true,"key":"B3VGBGcwFv"},{"type":"text","value":"—has been developed. R","key":"Ylnqt44su3"},{"type":"abbreviation","title":"Data Assimilation","children":[{"type":"text","value":"DA","key":"vWwZbCjnPj"}],"key":"mgw2y3AOVi"},{"type":"text","value":"SApp configures and integrates ","key":"rUiwAeLbaH"},{"type":"abbreviation","title":"Joint Effort for Data Assimilation Integration","children":[{"type":"text","value":"JEDI","key":"qZxXjtqrgi"}],"key":"F9gHCgcVRE"},{"type":"text","value":" components, providing the executables and tools needed to perform ","key":"bHQtEmCBsZ"},{"type":"abbreviation","title":"Rapid Refresh Forecast System","children":[{"type":"text","value":"RRFS","key":"hEFvZBGVbe"}],"key":"I2EMZMOzeF"},{"type":"text","value":"v2 data assimilation cycles.","key":"whpNxkVC9j"}],"key":"z4Kij67R9m"},{"type":"paragraph","position":{"start":{"line":5,"column":1},"end":{"line":5,"column":1}},"children":[{"type":"text","value":"To streamline reasearh and development testing as well as operational implmentation, an operation-oriented, community flexible end-to-end workflow, ","position":{"start":{"line":5,"column":1},"end":{"line":5,"column":1}},"key":"RFfaZyaxvJ"},{"type":"link","url":"https://github.com/NOAA-EMC/rrfs-workflow/tree/rrfs-mpas-jedi","position":{"start":{"line":5,"column":1},"end":{"line":5,"column":1}},"children":[{"type":"text","value":"rrfs-workflow","position":{"start":{"line":5,"column":1},"end":{"line":5,"column":1}},"key":"G8xC0CdQZO"}],"urlSource":"https://github.com/NOAA-EMC/rrfs-workflow/tree/rrfs-mpas-jedi","error":true,"key":"g83tY61LGF"},{"type":"text","value":" has been developed. rrfs-workflow enables both real-time and restrospective ","key":"DDp9Xb5Ub5"},{"type":"abbreviation","title":"Rapid Refresh Forecast System","children":[{"type":"text","value":"RRFS","key":"FPyAnRkOVd"}],"key":"vXFakNsWZf"},{"type":"text","value":"v2 experiments, accelerating the Research to Operation (R2O) transition and fostering collaborations between research and operation.","key":"K8AiqUFhgJ"}],"key":"htWxxOnXHP"}],"key":"kxUwzfXdP9"}],"key":"ayAW82fHeh"},"references":{"cite":{"order":[],"data":{}}},"footer":{"navigation":{"prev":{"title":"JEDI Overview","url":"/notebooks/overview-jedi","group":"Introduction"},"next":{"title":"Basic MPAS Analysis & Visualization with UXarray","url":"/notebooks/mpas-basic","group":"MPAS(Regional) Analysis and Visualization"}}},"domain":"http://localhost:3000"}