{"version":3,"kind":"Notebook","sha256":"ef1380f8f5c0da78bd90ddcd1652815609d33b0e1a5ad2fad7badae818e69608","slug":"notebooks.overview-mpas","location":"/notebooks/overview-mpas.ipynb","dependencies":[],"frontmatter":{"title":"MPAS Overview","content_includes_title":false,"kernelspec":{"name":"python3","display_name":"Python 3 (ipykernel)","language":"python"},"authors":[{"nameParsed":{"literal":"Guoqing Ge","given":"Guoqing","family":"Ge"},"name":"Guoqing Ge","id":"contributors-myst-generated-uid-0"},{"nameParsed":{"literal":"Orhan Eroglu","given":"Orhan","family":"Eroglu"},"name":"Orhan Eroglu","id":"contributors-myst-generated-uid-1"},{"nameParsed":{"literal":"Yan Pan","given":"Yan","family":"Pan"},"name":"Yan Pan","id":"contributors-myst-generated-uid-2"},{"nameParsed":{"literal":"Haidao Lin","given":"Haidao","family":"Lin"},"name":"Haidao Lin","id":"contributors-myst-generated-uid-3"},{"nameParsed":{"literal":"Stephen Asare","given":"Stephen","family":"Asare"},"name":"Stephen Asare","id":"contributors-myst-generated-uid-4"},{"nameParsed":{"literal":"Altug Karakurt","given":"Altug","family":"Karakurt"},"name":"Altug Karakurt","id":"contributors-myst-generated-uid-5"},{"nameParsed":{"literal":"Philip Chmielowiec","given":"Philip","family":"Chmielowiec"},"name":"Philip Chmielowiec","id":"contributors-myst-generated-uid-6"}],"open_access":true,"license":{"content":{"id":"CC-BY-4.0","url":"https://creativecommons.org/licenses/by/4.0/","name":"Creative Commons Attribution 4.0 International","free":true,"CC":true},"code":{"id":"Apache-2.0","url":"https://opensource.org/licenses/Apache-2.0","name":"Apache License 2.0","free":true,"osi":true}},"github":"https://github.com/projectpythia/mpas-jedi-cookbook","copyright":"2025","affiliations":[{"id":"UAlbany","name":"University at Albany (SUNY)","department":"Atmospheric and Environmental Sciences","url":"https://www.albany.edu/daes"},{"id":"CISL","name":"NSF National Center for Atmospheric Research","department":"Computational and Information Systems Lab","url":"https://www.cisl.ucar.edu"},{"id":"Unidata","name":"NSF Unidata","url":"https://www.unidata.ucar.edu"},{"id":"Argonne","name":"Argonne National Laboratory","department":"Environmental Science Division","url":"https://www.anl.gov/evs"},{"id":"CarbonPlan","name":"CarbonPlan","url":"https://carbonplan.org"},{"id":"NVIDIA","name":"NVIDIA Corporation","url":"https://www.nvidia.com/"}],"abbreviations":{"MPAS":"Model for Prediction Across Scales","JEDI":"Joint Effort for Data Assimilation Integration","RRFS":"Rapid Refresh Forecast System","DA":"Data Assimilation","CIRES":"Cooperative Institute for Research In Environmental Sciences","NOAA":"National Oceanic and Atmospheric Administration","GSL":"Global Systems Laboratory","NSF":"National Science Foundation","NCAR":"National Center for Atmospheric Research"},"numbering":{"title":{"offset":1}},"source_url":"https://github.com/projectpythia/mpas-jedi-cookbook/blob/main/notebooks/overview-mpas.ipynb","edit_url":"https://github.com/projectpythia/mpas-jedi-cookbook/edit/main/notebooks/overview-mpas.ipynb","thumbnail":"/mpas-jedi-cookbook/build/mpas_logo-a39b4a10608c7573f7adaa8f050abbbc.png","exports":[{"format":"ipynb","filename":"overview-mpas.ipynb","url":"/mpas-jedi-cookbook/build/overview-mpas-7f952bd34169acf8365a909b63e4e7d7.ipynb"}]},"widgets":{},"mdast":{"type":"root","children":[{"type":"block","kind":"notebook-content","children":[{"type":"paragraph","position":{"start":{"line":1,"column":1},"end":{"line":1,"column":1}},"children":[{"type":"text","value":"In this first section of the cookbook, we would like to provide an introduction to ","position":{"start":{"line":1,"column":1},"end":{"line":1,"column":1}},"key":"IjMetCwb75"},{"type":"link","url":"https://www2.mmm.ucar.edu/projects/mpas/site/index.html","position":{"start":{"line":1,"column":1},"end":{"line":1,"column":1}},"children":[{"type":"strong","position":{"start":{"line":1,"column":1},"end":{"line":1,"column":1}},"children":[{"type":"text","value":"M","position":{"start":{"line":1,"column":1},"end":{"line":1,"column":1}},"key":"HwtQGo5NJa"}],"key":"VrRKxcASsi"},{"type":"text","value":"odel for ","position":{"start":{"line":1,"column":1},"end":{"line":1,"column":1}},"key":"sElNlG3yNY"},{"type":"strong","position":{"start":{"line":1,"column":1},"end":{"line":1,"column":1}},"children":[{"type":"text","value":"P","position":{"start":{"line":1,"column":1},"end":{"line":1,"column":1}},"key":"rbKz8AZ79U"}],"key":"eXAM1qqWdG"},{"type":"text","value":"rediction ","position":{"start":{"line":1,"column":1},"end":{"line":1,"column":1}},"key":"qQGJ2f3l3X"},{"type":"strong","position":{"start":{"line":1,"column":1},"end":{"line":1,"column":1}},"children":[{"type":"text","value":"A","position":{"start":{"line":1,"column":1},"end":{"line":1,"column":1}},"key":"gYS0yHirG3"}],"key":"K1Vzf5FB7s"},{"type":"text","value":"cross ","position":{"start":{"line":1,"column":1},"end":{"line":1,"column":1}},"key":"S9QMPu0JuJ"},{"type":"strong","position":{"start":{"line":1,"column":1},"end":{"line":1,"column":1}},"children":[{"type":"text","value":"S","position":{"start":{"line":1,"column":1},"end":{"line":1,"column":1}},"key":"iGx5vp9kkP"}],"key":"LGpm4yIwIV"},{"type":"text","value":"cales (MPAS)","position":{"start":{"line":1,"column":1},"end":{"line":1,"column":1}},"key":"TLuKHiXRYA"}],"urlSource":"https://www2.mmm.ucar.edu/projects/mpas/site/index.html","key":"sQWa1shJ4L"},{"type":"text","value":". Please note, instead of trying to replicate what has already been made available by the ","key":"bwT8FeJ9fA"},{"type":"abbreviation","title":"Model for Prediction Across Scales","children":[{"type":"text","value":"MPAS","key":"Iv6TFvZ7K3"}],"key":"bnCj4VpKHQ"},{"type":"text","value":" user and developer community, we will point this this cookrbook’s readers to the right direction to access such resources.","key":"JeYtWK9f4k"}],"key":"FeiP9M1axu"},{"type":"image","url":"/mpas-jedi-cookbook/build/mpas_logo-a39b4a10608c7573f7adaa8f050abbbc.png","alt":"MPAS logo","width":"200px","align":"center","key":"xC1Lkq0Ds8","urlSource":"images/mpas_logo.png"}],"key":"aEwZNH0LNa"},{"type":"block","kind":"notebook-content","children":[{"type":"heading","depth":3,"position":{"start":{"line":1,"column":1},"end":{"line":1,"column":1}},"children":[{"type":"text","value":"In this section, you’ll not code but learn:","position":{"start":{"line":1,"column":1},"end":{"line":1,"column":1}},"key":"kekRHQb35j"}],"identifier":"in-this-section-youll-not-code-but-learn","label":"In this section, you’ll not code but learn:","html_id":"in-this-section-youll-not-code-but-learn","implicit":true,"key":"u5qNF3UOCX"},{"type":"list","ordered":false,"spread":false,"position":{"start":{"line":3,"column":1},"end":{"line":5,"column":1}},"children":[{"type":"listItem","spread":true,"position":{"start":{"line":3,"column":1},"end":{"line":3,"column":1}},"children":[{"type":"paragraph","children":[{"type":"text","value":"What is ","key":"Be6QSH9Tyv"},{"type":"abbreviation","title":"Model for Prediction Across Scales","children":[{"type":"text","value":"MPAS","key":"N9GBhQVKDe"}],"key":"PAbRxGRMQY"},{"type":"text","value":"?","key":"GQEId9jZTD"}],"key":"Kf6OtsPD8l"}],"key":"VxEfjjybIe"},{"type":"listItem","spread":true,"position":{"start":{"line":4,"column":1},"end":{"line":5,"column":1}},"children":[{"type":"paragraph","children":[{"type":"text","value":"Why ","key":"axP6lMGO41"},{"type":"abbreviation","title":"Model for Prediction Across Scales","children":[{"type":"text","value":"MPAS","key":"ZfpEXtVDdE"}],"key":"qdB7ZipH5X"},{"type":"text","value":"?","key":"gTfacsfy41"}],"key":"QkvMc4ThQ2"}],"key":"XyQNSVDs6d"}],"key":"TkWjFeaaq7"},{"type":"heading","depth":3,"position":{"start":{"line":6,"column":1},"end":{"line":6,"column":1}},"children":[{"type":"text","value":"Related Documentation","position":{"start":{"line":6,"column":1},"end":{"line":6,"column":1}},"key":"DvUjoxcwOe"}],"identifier":"related-documentation","label":"Related Documentation","html_id":"related-documentation","implicit":true,"key":"rQwspbcsxP"},{"type":"list","ordered":false,"spread":false,"position":{"start":{"line":8,"column":1},"end":{"line":12,"column":1}},"children":[{"type":"listItem","spread":true,"position":{"start":{"line":8,"column":1},"end":{"line":8,"column":1}},"children":[{"type":"paragraph","children":[{"type":"link","url":"https://www2.mmm.ucar.edu/projects/mpas/site/index.html","position":{"start":{"line":8,"column":1},"end":{"line":8,"column":1}},"children":[{"type":"text","value":"MPAS Homepage","position":{"start":{"line":8,"column":1},"end":{"line":8,"column":1}},"key":"dOQSmAYDSz"}],"urlSource":"https://www2.mmm.ucar.edu/projects/mpas/site/index.html","key":"hJQgojHGnY"}],"key":"MvuNcgwhDy"}],"key":"ck76dWiVqQ"},{"type":"listItem","spread":true,"position":{"start":{"line":9,"column":1},"end":{"line":9,"column":1}},"children":[{"type":"paragraph","children":[{"type":"link","url":"https://www2.mmm.ucar.edu/projects/mpas/site/documentation.html","position":{"start":{"line":9,"column":1},"end":{"line":9,"column":1}},"children":[{"type":"text","value":"MPAS Documentation","position":{"start":{"line":9,"column":1},"end":{"line":9,"column":1}},"key":"T1AUJOb4wG"}],"urlSource":"https://www2.mmm.ucar.edu/projects/mpas/site/documentation.html","key":"v1CFvLRkxs"}],"key":"TYEbn2T2zi"}],"key":"SPt4YNc1Pk"},{"type":"listItem","spread":true,"position":{"start":{"line":10,"column":1},"end":{"line":10,"column":1}},"children":[{"type":"paragraph","children":[{"type":"link","url":"https://www2.mmm.ucar.edu/projects/mpas/site/publications.html","position":{"start":{"line":10,"column":1},"end":{"line":10,"column":1}},"children":[{"type":"text","value":"MPAS Publications","position":{"start":{"line":10,"column":1},"end":{"line":10,"column":1}},"key":"IVgKhsAxj3"}],"urlSource":"https://www2.mmm.ucar.edu/projects/mpas/site/publications.html","key":"gwhVlX0zbO"}],"key":"JQz8VFNFxI"}],"key":"OKpmJEDCep"},{"type":"listItem","spread":true,"position":{"start":{"line":11,"column":1},"end":{"line":12,"column":1}},"children":[{"type":"paragraph","children":[{"type":"link","url":"https://forum.mmm.ucar.edu/","position":{"start":{"line":11,"column":1},"end":{"line":11,"column":1}},"children":[{"type":"text","value":"MPAS Support Forum","position":{"start":{"line":11,"column":1},"end":{"line":11,"column":1}},"key":"OsVEWoJaYs"}],"urlSource":"https://forum.mmm.ucar.edu/","key":"WeBVEtiplS"}],"key":"RPBQjMHaSY"}],"key":"PY5Cq6zHz1"}],"key":"MMQ0XZUfkJ"},{"type":"heading","depth":3,"position":{"start":{"line":13,"column":1},"end":{"line":13,"column":1}},"children":[{"type":"text","value":"Prerequisites","position":{"start":{"line":13,"column":1},"end":{"line":13,"column":1}},"key":"yHS7Q8XNnQ"}],"identifier":"prerequisites","label":"Prerequisites","html_id":"prerequisites","implicit":true,"key":"ilscbCYJ4b"},{"type":"table","position":{"start":{"line":15,"column":1},"end":{"line":17,"column":1}},"children":[{"type":"tableRow","position":{"start":{"line":15,"column":1},"end":{"line":15,"column":1}},"children":[{"type":"tableCell","header":true,"position":{"start":{"line":15,"column":1},"end":{"line":15,"column":1}},"children":[{"type":"text","value":"Concepts","position":{"start":{"line":15,"column":1},"end":{"line":15,"column":1}},"key":"bQbj046yQK"}],"key":"RM94mIAD8p"},{"type":"tableCell","header":true,"position":{"start":{"line":15,"column":1},"end":{"line":15,"column":1}},"children":[{"type":"text","value":"Importance","position":{"start":{"line":15,"column":1},"end":{"line":15,"column":1}},"key":"biS22tUrMJ"}],"key":"RbCRanPzcT"},{"type":"tableCell","header":true,"position":{"start":{"line":15,"column":1},"end":{"line":15,"column":1}},"children":[{"type":"text","value":"Notes","position":{"start":{"line":15,"column":1},"end":{"line":15,"column":1}},"key":"ldOgwh3gTz"}],"key":"Rbl8DacdMk"}],"key":"RUoLKx48lS"},{"type":"tableRow","position":{"start":{"line":17,"column":1},"end":{"line":17,"column":1}},"children":[{"type":"tableCell","position":{"start":{"line":17,"column":1},"end":{"line":17,"column":1}},"children":[{"type":"link","url":"https://projectpythia.org/unstructured-grid-viz-cookbook/notebooks/foundations/unstructured-grids/","position":{"start":{"line":17,"column":1},"end":{"line":17,"column":1}},"children":[{"type":"text","value":"Introduction to Unstructured Grids","position":{"start":{"line":17,"column":1},"end":{"line":17,"column":1}},"key":"XhMD9KdRH0"}],"urlSource":"https://projectpythia.org/unstructured-grid-viz-cookbook/notebooks/foundations/unstructured-grids/","key":"A7wa1ATYko"}],"key":"yJ6aOXmJPx"},{"type":"tableCell","position":{"start":{"line":17,"column":1},"end":{"line":17,"column":1}},"children":[{"type":"text","value":"Helpful","position":{"start":{"line":17,"column":1},"end":{"line":17,"column":1}},"key":"kxIChCJlQ0"}],"key":"jTNbjBxLqI"},{"type":"tableCell","position":{"start":{"line":17,"column":1},"end":{"line":17,"column":1}},"children":[],"key":"f8Y8iJk5al"}],"key":"UXPjTuLbuO"}],"key":"Bg9GpVGVFF"},{"type":"paragraph","position":{"start":{"line":19,"column":1},"end":{"line":19,"column":1}},"children":[{"type":"strong","position":{"start":{"line":19,"column":1},"end":{"line":19,"column":1}},"children":[{"type":"text","value":"Time to learn","position":{"start":{"line":19,"column":1},"end":{"line":19,"column":1}},"key":"kwSRYiG7y3"}],"key":"u4w4P4oUN2"},{"type":"text","value":": 10 minutes","position":{"start":{"line":19,"column":1},"end":{"line":19,"column":1}},"key":"qchKOwNLlT"}],"key":"MnZQ1pPFRu"}],"key":"QPcSZrlhAr"},{"type":"block","kind":"notebook-content","children":[{"type":"thematicBreak","position":{"start":{"line":1,"column":1},"end":{"line":1,"column":1}},"key":"KqnNDEogWk"}],"key":"YJWixMgHiZ"},{"type":"block","kind":"notebook-content","children":[{"type":"heading","depth":2,"position":{"start":{"line":1,"column":1},"end":{"line":1,"column":1}},"children":[{"type":"text","value":"What is ","key":"S514or4PMl"},{"type":"abbreviation","title":"Model for Prediction Across Scales","children":[{"type":"text","value":"MPAS","key":"wm5UYNO3or"}],"key":"k3FCzeldjX"},{"type":"text","value":"?","key":"nMlQQLmLjA"}],"identifier":"what-is-mpas","label":"What is MPAS?","html_id":"what-is-mpas","implicit":true,"key":"hqXbs3rwyk"}],"key":"NQOGajfQPC"},{"type":"block","kind":"notebook-content","children":[{"type":"paragraph","position":{"start":{"line":1,"column":1},"end":{"line":1,"column":1}},"children":[{"type":"text","value":"The Model for Prediction Across Scales (","key":"oGaKhNhsHD"},{"type":"abbreviation","title":"Model for Prediction Across Scales","children":[{"type":"text","value":"MPAS","key":"bPCdHRiySm"}],"key":"cANEuvHmqU"},{"type":"text","value":") is a collaborative project for developing atmosphere, ocean and other earth-system simulation components for use in climate, regional climate and weather studies.","key":"I5UdfeIAgu"}],"key":"wcYxrZMRIB"},{"type":"paragraph","position":{"start":{"line":3,"column":1},"end":{"line":3,"column":1}},"children":[{"type":"text","value":"The defining features of ","key":"xxqhJLix4g"},{"type":"abbreviation","title":"Model for Prediction Across Scales","children":[{"type":"text","value":"MPAS","key":"gV99dcJbu4"}],"key":"hIFWOctAQO"},{"type":"text","value":" are the unstructured ","key":"PT9rG7u4Vi"},{"type":"link","url":"https://public.lanl.gov/ringler/Voronoi.html","position":{"start":{"line":3,"column":1},"end":{"line":3,"column":1}},"children":[{"type":"text","value":"Voronoi meshes","position":{"start":{"line":3,"column":1},"end":{"line":3,"column":1}},"key":"P9THEr0t9k"}],"urlSource":"https://public.lanl.gov/ringler/Voronoi.html","key":"rhQmeAguwA"},{"type":"text","value":" and ","position":{"start":{"line":3,"column":1},"end":{"line":3,"column":1}},"key":"UQxp65gpnB"},{"type":"link","url":"https://mpas-dev.github.io/files/graphics/cgrid.pdf","position":{"start":{"line":3,"column":1},"end":{"line":3,"column":1}},"children":[{"type":"text","value":"C-grid","position":{"start":{"line":3,"column":1},"end":{"line":3,"column":1}},"key":"tk8wHpYVB5"}],"urlSource":"https://mpas-dev.github.io/files/graphics/cgrid.pdf","key":"Ww9o31ClsT"},{"type":"text","value":" discretization used as the basis for many of the model components. The unstructured Voronoi meshes, formally Spherical Centriodal Voronoi Tesselations (SCVTs), allow for both quasi-uniform discretization of the sphere and local refinement. The C-grid discretization, where the normal component of velocity on cell edges is prognosed, is especially well-suited for higher-resolution, mesoscale atmosphere and ocean simulations.","position":{"start":{"line":3,"column":1},"end":{"line":3,"column":1}},"key":"PolxoLsIiK"}],"key":"PN7t9HeEK1"},{"type":"paragraph","position":{"start":{"line":5,"column":1},"end":{"line":5,"column":1}},"children":[{"type":"text","value":"The land ice model takes advantage of the SCVT-dual mesh, which is a triangular Delaunay tessellation appropriate for use with Finite-Element-based discretizations.","position":{"start":{"line":5,"column":1},"end":{"line":5,"column":1}},"key":"bzmEUYJAEE"}],"key":"khQ7Zjr3I9"},{"type":"paragraph","position":{"start":{"line":7,"column":1},"end":{"line":7,"column":1}},"children":[{"type":"text","value":"Be sure to check out the ","position":{"start":{"line":7,"column":1},"end":{"line":7,"column":1}},"key":"MfrPIvrsvD"},{"type":"link","url":"https://www2.mmm.ucar.edu/projects/mpas/site/index.html","position":{"start":{"line":7,"column":1},"end":{"line":7,"column":1}},"children":[{"type":"text","value":"MPAS home page","position":{"start":{"line":7,"column":1},"end":{"line":7,"column":1}},"key":"quucl5wg6B"}],"urlSource":"https://www2.mmm.ucar.edu/projects/mpas/site/index.html","key":"irQ4oWqQui"},{"type":"text","value":" and the References at the end of this section for further details.","position":{"start":{"line":7,"column":1},"end":{"line":7,"column":1}},"key":"EU2tAjUjNd"}],"key":"sAzONxjw2O"},{"type":"image","url":"/mpas-jedi-cookbook/build/f34a36cfa802fae40ae482477b083a9b.png","alt":"MPAS","width":"50%","align":"left","key":"sD7b41On6Q","urlSource":"https://mpas-dev.github.io/atmosphere/MPAS-var-res_mesh.png"},{"type":"image","url":"/mpas-jedi-cookbook/build/mpas-c-grid-bc5d78b0fb78f322c730947947b46f5e.png","alt":"MPAS C-grid","width":"50%","align":"right","key":"Es6DdJI7lm","urlSource":"./images/mpas-c-grid.png"},{"type":"paragraph","position":{"start":{"line":21,"column":1},"end":{"line":21,"column":1}},"children":[{"type":"strong","position":{"start":{"line":21,"column":1},"end":{"line":21,"column":1}},"children":[{"type":"text","value":"Image credit","position":{"start":{"line":21,"column":1},"end":{"line":21,"column":1}},"key":"RnTPoqzAlY"}],"key":"nt8B6j6nSi"},{"type":"text","value":": ","position":{"start":{"line":21,"column":1},"end":{"line":21,"column":1}},"key":"nwLofFRqha"},{"type":"link","url":"https://mpas-dev.github.io/atmosphere/atmosphere.html","position":{"start":{"line":21,"column":1},"end":{"line":21,"column":1}},"children":[{"type":"text","value":"https://​mpas​-dev​.github​.io​/atmosphere​/atmosphere​.html","position":{"start":{"line":21,"column":1},"end":{"line":21,"column":1}},"key":"UB6zVvRT6t"}],"urlSource":"https://mpas-dev.github.io/atmosphere/atmosphere.html","key":"ImSRSOU43a"}],"key":"oIp4LZl5N0"}],"key":"RlI1qTo5wD"},{"type":"block","kind":"notebook-content","children":[{"type":"heading","depth":2,"position":{"start":{"line":1,"column":1},"end":{"line":1,"column":1}},"children":[{"type":"text","value":"Why ","key":"YHpUURCXp5"},{"type":"abbreviation","title":"Model for Prediction Across Scales","children":[{"type":"text","value":"MPAS","key":"drPAywCL8U"}],"key":"PcnZ4pSy4U"},{"type":"text","value":"?","key":"ZDly0pH3ld"}],"identifier":"why-mpas","label":"Why MPAS?","html_id":"why-mpas","implicit":true,"key":"Jaugshr1XS"}],"key":"Ivdt9c94HX"},{"type":"block","kind":"notebook-content","children":[{"type":"paragraph","position":{"start":{"line":1,"column":1},"end":{"line":1,"column":1}},"children":[{"type":"text","value":"The key features of ","key":"i9Bp7QbbV0"},{"type":"abbreviation","title":"Model for Prediction Across Scales","children":[{"type":"text","value":"MPAS","key":"wg7jl6PmeL"}],"key":"dxdjztYR18"},{"type":"text","value":" are:","key":"KuP3mHKx5g"}],"key":"HPEZgMFeDG"},{"type":"list","ordered":false,"spread":false,"position":{"start":{"line":3,"column":1},"end":{"line":6,"column":1}},"children":[{"type":"listItem","spread":true,"position":{"start":{"line":3,"column":1},"end":{"line":3,"column":1}},"children":[{"type":"paragraph","children":[{"type":"text","value":"Suitability for global and regional analysis","position":{"start":{"line":3,"column":1},"end":{"line":3,"column":1}},"key":"VG97kAU1Cy"}],"key":"ZLjHaWTuUw"}],"key":"zWKd04WznR"},{"type":"listItem","spread":true,"position":{"start":{"line":4,"column":1},"end":{"line":4,"column":1}},"children":[{"type":"paragraph","children":[{"type":"text","value":"Applicability to weather and climate research","position":{"start":{"line":4,"column":1},"end":{"line":4,"column":1}},"key":"ZeVZjDyFA8"}],"key":"Tm0yDNPq7p"}],"key":"FDdPvWhHre"},{"type":"listItem","spread":true,"position":{"start":{"line":5,"column":1},"end":{"line":5,"column":1}},"children":[{"type":"paragraph","children":[{"type":"text","value":"Variable resolution","position":{"start":{"line":5,"column":1},"end":{"line":5,"column":1}},"key":"AaJMynoVdK"}],"key":"p17IRBRsZR"}],"key":"fAR98340xx"},{"type":"listItem","spread":true,"position":{"start":{"line":6,"column":1},"end":{"line":6,"column":1}},"children":[{"type":"paragraph","children":[{"type":"text","value":"Scalability","position":{"start":{"line":6,"column":1},"end":{"line":6,"column":1}},"key":"pebuPdURvd"}],"key":"hgWBFTOVPw"}],"key":"yY59jYo85Q"}],"key":"XTJKKtNkV6"}],"key":"FpoTUmEQdK"},{"type":"block","kind":"notebook-content","children":[{"type":"heading","depth":2,"position":{"start":{"line":1,"column":1},"end":{"line":1,"column":1}},"children":[{"type":"text","value":"References","position":{"start":{"line":1,"column":1},"end":{"line":1,"column":1}},"key":"x46xxhel7A"}],"identifier":"references","label":"References","html_id":"references","implicit":true,"key":"tMUQ6spB3Q"},{"type":"paragraph","position":{"start":{"line":3,"column":1},"end":{"line":3,"column":1}},"children":[{"type":"link","url":"https://www2.mmm.ucar.edu/projects/mpas/mpas_website_linked_files/mpas_meshspec.pdf","position":{"start":{"line":3,"column":1},"end":{"line":3,"column":1}},"children":[{"type":"text","value":"MPAS Mesh Specification Version 1.0, 2015","position":{"start":{"line":3,"column":1},"end":{"line":3,"column":1}},"key":"r57AoHSW2Z"}],"urlSource":"https://www2.mmm.ucar.edu/projects/mpas/mpas_website_linked_files/mpas_meshspec.pdf","key":"kIDeQDl5Cu"}],"key":"w9bcU8VBUp"}],"key":"HstATkd3iK"},{"type":"block","kind":"notebook-content","children":[{"type":"heading","depth":2,"position":{"start":{"line":1,"column":1},"end":{"line":1,"column":1}},"children":[{"type":"text","value":"What is next?","position":{"start":{"line":1,"column":1},"end":{"line":1,"column":1}},"key":"dU5xbFl9cK"}],"identifier":"what-is-next","label":"What is next?","html_id":"what-is-next","implicit":true,"key":"tZ1iTULYe0"},{"type":"paragraph","position":{"start":{"line":3,"column":1},"end":{"line":3,"column":1}},"children":[{"type":"text","value":"The ","position":{"start":{"line":3,"column":1},"end":{"line":3,"column":1}},"key":"Ku89f0TbHi"},{"type":"link","url":"/notebooks/overview-jedi","position":{"start":{"line":3,"column":1},"end":{"line":3,"column":1}},"children":[{"type":"text","value":"next section","position":{"start":{"line":3,"column":1},"end":{"line":3,"column":1}},"key":"cPk2VQyFC9"}],"urlSource":"overview-jedi","dataUrl":"/notebooks.overview-jedi.json","internal":true,"protocol":"file","key":"gXVEIduXyg"},{"type":"text","value":" will provide an overview of the The Joint Effort for Data assimilation (","key":"f3jh1g01za"},{"type":"abbreviation","title":"Joint Effort for Data Assimilation Integration","children":[{"type":"text","value":"JEDI","key":"HOCtADwYSx"}],"key":"URlYjWaxde"},{"type":"text","value":").","key":"UTlfw8lXyu"}],"key":"JITdiFBzTC"}],"key":"PPaQONEb18"}],"key":"icJRjWRrFG"},"references":{"cite":{"order":[],"data":{}}},"footer":{"navigation":{"prev":{"title":"How to Cite This Cookbook","url":"/notebooks/how-to-cite","group":"Preamble"},"next":{"title":"JEDI Overview","url":"/notebooks/overview-jedi","group":"Introduction"}}},"domain":"http://localhost:3000"}